codecollector/__init__.py
codecollector/cli.py
codecollector/collector.py
codecollector/config.py
codecollector-0.1.0.dist-info/LICENCE
codecollector-0.1.0.dist-info/METADATA
codecollector-0.1.0.dist-info/WHEEL
codecollector-0.1.0.dist-info/entry_points.txt
codecollector-0.1.0.dist-info/top_level.txt
codecollector-0.1.0.dist-info/RECORD
