Metadata-Version: 2.1
Name: codecollector
Version: 0.1.0
Summary: A CLI tool to aggregate and organize code files from complex projects
Home-page: https://github.com/DLOVRIC2/code_collector
Author: Domagoj Lovric
Author-email: dominic@algorise.co.uk
Project-URL: Bug Tracker, https://github.com/DLOVRIC2/code_collector/issues
Keywords: code aggregator organizer cli development
Classifier: Development Status :: 3 - Alpha
Classifier: Intended Audience :: Developers
Classifier: License :: OSI Approved :: MIT License
Classifier: Operating System :: OS Independent
Classifier: Programming Language :: Python :: 3
Classifier: Programming Language :: Python :: 3.6
Classifier: Programming Language :: Python :: 3.7
Classifier: Programming Language :: Python :: 3.8
Classifier: Programming Language :: Python :: 3.9
Classifier: Programming Language :: Python :: 3.10
Classifier: Programming Language :: Python :: 3.11
Requires-Python: >=3.6
License-File: LICENCE
Requires-Dist: click
Requires-Dist: PyYAML
Requires-Dist: prompt-toolkit
